<?xml version = '1.0'  encoding = 'ISO-8859-1'  standalone = 'yes' ?>
<!-- PlotDigitizer data file: created on Fri Mar 09 09:24:04 GMT 2018 -->
<data>
<image file='BrouilletteFig6B.png' />
<axesnames x='X'  y='Y' />
<calibpoints minXaxisX='306.0' minXaxisY='975.0' maxXaxisX='1172.0' maxXaxisY='979.0' minYaxisX='262.0' minYaxisY='910.0' maxYaxisX='262.0' maxYaxisY='240.0' aX1='-100.0' aX2='0.0' aY1='0.0' aY2='1.0' isXLog='false' isYLog='false' />
<point n='0' x='304.0' y='256.0' dx='-100.61442293845637' dy='0.9764089483299438' />
<point n='1' x='390.0' y='251.0' dx='-90.68658563253028' dy='0.9844645134604115' />
<point n='2' x='477.0' y='259.0' dx='-80.63634375683358' dy='0.9731239874530351' />
<point n='3' x='563.0' y='279.0' dx='-70.69517261977781' dy='0.9438661197476819' />
<point n='4' x='650.0' y='343.0' dx='-60.615062962350606' dy='0.8489435041880666' />
<point n='5' x='737.0' y='530.0' dx='-50.469350855765285' dy='0.5704387990762124' />
<point n='6' x='823.0' y='751.0' dx='-40.42097571642674' dy='0.24118093137085928' />
<point n='7' x='910.0' y='856.0' dx='-30.318998575946836' dy='0.08506428596049775' />
<point n='8' x='997.0' y='874.0' dx='-20.263423167798265' dy='0.05879838681879268' />
<point n='9' x='1084.0' y='912.0' dx='-10.197180694745938' dy='0.0026817414084314706' />
<point n='10' x='1171.0' y='909.0' dx='-0.15280570474632782' dy='0.007759125848816106' />
</data>
